scoreq/__init__.py
scoreq/__main__.py
scoreq/scoreq.py
scoreq-1.0.1.dist-info/METADATA
scoreq-1.0.1.dist-info/WHEEL
scoreq-1.0.1.dist-info/top_level.txt
scoreq-1.0.1.dist-info/RECORD
