Metadata-Version: 2.4
Name: scoreq
Version: 1.0.1
Summary: A Python package for advanced speech quality assessment using the SCOREQ model
Author-email: Alessandro Ragano <alessandroragano@gmail.com>
License: MIT License
Project-URL: Homepage, https://github.com/alessandroragano/scoreq
Classifier: Programming Language :: Python :: 3
Classifier: Operating System :: OS Independent
Requires-Python: >=3.10
Requires-Dist: onnxruntime>=1.18.0
Requires-Dist: numpy>=2.0
Requires-Dist: torchaudio
Requires-Dist: tqdm
Requires-Dist: click>=8.1.7
Requires-Dist: soundfile
Provides-Extra: pytorch
Requires-Dist: torch; extra == "pytorch"
Requires-Dist: fairseq==0.12.2; extra == "pytorch"
Requires-Dist: omegaconf==2.0.6; extra == "pytorch"
Requires-Dist: antlr4-python3-runtime==4.8; extra == "pytorch"
Provides-Extra: gpu
Requires-Dist: onnxruntime-gpu>=1.18.0; extra == "gpu"
